sciencelinker/__init__.py
sciencelinker/geo_names.py
sciencelinker/kg_dbpedia.py
sciencelinker/kg_generic.py
sciencelinker/kg_wikidata.py
sciencelinker/lda_gensim.py
sciencelinker/mpr_client.py
sciencelinker/ner_dbpspot.py
sciencelinker/processing_log.py
sciencelinker/request_cache.py
sciencelinker-0.1.0.dist-info/LICENSE
sciencelinker-0.1.0.dist-info/METADATA
sciencelinker-0.1.0.dist-info/WHEEL
sciencelinker-0.1.0.dist-info/top_level.txt
sciencelinker-0.1.0.dist-info/RECORD
